{
    "Framework":
    {   
        "sample_size": 50,
        "tau": 1,
        "SEmax": 500
    },
    "MEMO":
    {
        "maxEvaluations": 50,
        "populationSize": 50,
        "offspringSize": 50
    },
    "Crossover":
    {
        "distribution": 20,
        "probability": 0.9
    },
    "Mutation":
    {
        "distribution": 20,
        "probability": 0.5
    },
    "Selection":
    {
        "tournament_size": 25
    },
    "Problem":
    {
        "k": 5,
        "m": 3
    }
}